test/dut.v
`timescale 1 ns / 100 ps

module dut (
  input wire  clk,enable,
  input wire  reset,
  input wire  start,
  input wire  configure,
  input wire  [7:0] din,
  input wire  [1:0 ]connectType, 			
  input wire  [7:0] reconnectInt, 			
  input wire  [15:0] starttime, 			
  input wire  [15:0] endtime, 			
  input wire  [5:0] beginstring, 			
  input wire  [5:0] defaultApplVerId, 		
  input wire  [255:0] senderCompId, 		
  input wire  [255:0] targetCompId, 		
  input wire  [15:0] hostAddr, 				 
  input wire  [7:0] heartBeatInt, 		

  output reg [7:0] dout,
  output reg       valid
);

always @ (posedge clk)
  begin
    dout  <= din;
    valid  <= enable;
  end

endmodule
           
/*
reg [1:0 ]connectType;			
reg [7:0] reconnectInt;			
reg [15:0] starttime;			
reg [15:0] endtime;			
reg [5:0] beginstring;			
reg [5:0] defaultApplVerId;		
reg [255:0] senderCompId;		
reg [255:0] targetCompId;		
reg [15:0] hostAddr;				 
reg [7:0] heartBeatInt;			
*/

test/bench.v
/*
 ----------------------------------------------------------------------------- -
 -
 - FILE        : bench.v 
 - Design      : FIX Engine
 - Description : Automated testbench for design
 - Author      : Adil Sadik <sadik.adil@gmail.com, ams2378@columbia.edu> 
 -
 -----------------------------------------------------------------------------
 -
 - Created     : 03/26/2013
 - Revision    : 03/30/2013 
 -		 Included Verilog-event feature for better control 
 -		 over execution flow   
 -
 -		
 -
 -----------------------------------------------------------------------------
 -
 -  Dependency  : dut.v, init_in.txt, init_out.txt
 -  Output Log  : monitor.txt
 -   
 -  Status	: Only deals with Initiator side. 
 -		  Good (compiling and dumping waveforms in desired format)
 -  TODO	: Need to add acceptor side (should be very trivial)	  
 -   		  Need real DUT for verification (in progress)
 -   
 -  Instruction : For simulation, run "sh runsim.sh" from command line 
 -   
 -----------------------------------------------------------------------------
*/

`timescale 1 ns / 100 ps

module bench;

// decleare dut in/out ports
reg enable;
reg clk;
reg reset;
reg configure;
reg start;
reg [7:0] din;

reg [1:0 ]connectType;			// 01- initiator, 10- acceptor
reg [7:0] reconnectInt;			// in second (exp: 60 second)
reg [15:0] starttime;			// in hh mn sc
reg [15:0] endtime;			// in hh mn sc
reg [5:0] beginstring;			// (example) 4.4 - 100 100
reg [5:0] defaultApplVerId;		// 4.3 - 100 011
reg [255:0] senderCompId;		// sent as ASCII (max - 256 bits)
reg [255:0] targetCompId;		// sent as ASCII (max - 256 bits)
reg [15:0] hostAddr;			// (example) - 16 bit	 
reg [7:0] heartBeatInt;			// (example) - 8 bit

wire [7:0] dout;
wire valid;

// instantiate dut
dut dut (clk,enable,reset, start, configure,din, connectType, reconnectInt, starttime, endtime, beginstring, defaultApplVerId,
	 senderCompId, targetCompId, hostAddr, heartBeatInt, dout,valid);

// internal variables and events
integer statusI,statusO, mon;
reg [7:0] exp;
integer in,out,cfg;
integer dut_error;

event reset_enable;
event reset_done;
event exit_sim;
event configure_enable;
event configure_done;
event start_initiator;
event start_acceptor;
event error;
event initiation_trigger_sent;

// clock generator
always # 1 clk = ~clk;

// dumping waveforms
initial 
begin
  	$dumpfile ("dut.vcd");
  	$dumpvars;
end

//enable if compiling with VCS
//initial $vcdpluson;		 

// initialization
initial begin
	$display ("\n");
	$display ("################################################### \n");
  	$display ("STARTING SIMULATION\n");
  	clk = 0;
  	enable = 0;
  	din = 0;
  	exp = 0;
	cfg = $fopen("clientconfig.txt","r");
  	in  = $fopen("init_in.txt","r");
  	out = $fopen("init_in.txt","r");
  	mon = $fopen("monitor.txt","w");
end

// test flow:  
// start with a reset (after warmup cycle)
// configure DUT 
// upon configuration, tell DUT to initiate a fix session by sending logon
// exit in case of any error
// log information regarding error
initial begin
  	#10 -> reset_enable;
  	@ (reset_done);
  	-> configure_enable;	
  	@ (configure_done);
  	#10 -> start_initiator;
  	@ (error);
  	-> exit_sim;
end

// applying reset logic
initial
forever begin
 	@ (reset_enable);
 	@ (negedge clk)
 	$display ("Applying reset @ %0dns", $time);
   	reset = 1;
 	@ (negedge clk)
   	reset = 0;
 	$display ("Came out of Reset @ %0dns", $time);
 	-> reset_done;
end

// start configuration 
initial 
forever begin
	@ (configure_enable);
	@ (negedge clk)
	$display ("configuring DUT @ %0dns", $time);
	configure = 1;
	 statusI = $fscanf(cfg, "%b\n" ,connectType);
	 statusI = $fscanf(cfg, "%b\n" ,reconnectInt);
	 statusI = $fscanf(cfg, "%b\n" ,starttime);
	 statusI = $fscanf(cfg, "%b\n" ,endtime);
	 statusI = $fscanf(cfg, "%b\n" ,beginstring);
	 statusI = $fscanf(cfg, "%b\n" ,defaultApplVerId);
	 statusI = $fscanf(cfg, "%b\n" ,senderCompId);
	 statusI = $fscanf(cfg, "%b\n" ,targetCompId);
	 statusI = $fscanf(cfg, "%b\n" ,hostAddr);
	 statusI = $fscanf(cfg, "%b\n" ,heartBeatInt);		
	@ (negedge clk)
	configure = 0;
	#2 -> configure_done;			// 2 cycles to do configuration
end  

// initiate initiator  
initial 
forever begin 
	@ (start_initiator);
	@ (negedge clk)
	$display ("Initiating a new connection @ %0dns", $time);
	start = 1;
	@ (negedge clk)
	start = 0;
	-> initiation_trigger_sent;
end

// exiting simulation
initial
	@ (exit_sim)  begin
	$display ("Terminating simulation @ %0dns ", $time);
 	if (dut_error == 0) begin
  		$display ("Simulation Result : PASSED");
 	end else begin
     		$display ("Simulation Result : FAILED");
     		$display("       Got  %h",dout);
     		$display("       Exp  %h",exp);
 	end
 	$display ("################################################### \n");
 	#1 $finish;
end


// initiator execution starts here; driving DUT input ports
initial
forever begin
	@(initiation_trigger_sent)
   while (!($feof(in))) begin
	@ (negedge clk)
	$display ("DUT receiving inputs from acceptor @ %0dns", $time);
	enable = 1;
	statusI = $fscanf(in,"%h\n",din[7:0]);
	@ (negedge clk)
	enable = 0;
	if (din == 8'h3b) begin			// end of one FIX message
		#10;				// wait for heartbeat
	end
  end
	$fclose(in);
	$fclose(out);
	#10 -> exit_sim; 
end


// DUT output monitor and compare logic
always @ (posedge clk)
	if (reset == 1) begin
		dut_error = (dout != 8'h00) ? 1 : 0;
		if (dut_error)	-> error;		
	end else if (valid == 1) begin
   		statusO = $fscanf(out,"%h\n",exp[7:0]);
		dut_error = (dout != exp) ? 1 : 0;		
		if (dut_error)	-> error;
		else begin
 	   	$display("Match : input and output match @ %0dns  ",$time);
     		$display("       Got  %h",dout);
     		$display("       Exp  %h",exp);
		end		
   	end 

endmodule




/*

// reference outputs - to be matched with DUT outputs
always @ (posedge clk) 
	if (reset == 1)
		exp <= 8'h00;
	else if (start == 1) begin
		#10     statusO = $fscanf(out,"%h\n",exp[7:0]);		// 10 cycles to generate valid outputs by DUT 
	else if (enable == 1) begin
		

	end 

*/

test/dut.vcd
$date
	Sun Mar 31 22:51:17 2013
$end

$version
	Synopsys VCS version F-2011.12_Full64
$end

$timescale
	100ps
$end

$comment Csum: 1 0e5d74a735456f64 $end


$scope module bench $end
$var reg 1 ! enable $end
$var reg 1 " clk $end
$var reg 1 # reset $end
$var reg 1 $ configure $end
$var reg 1 % start $end
$var reg 8 & din [7:0] $end
$var reg 2 ' connectType [1:0] $end
$var reg 8 ( reconnectInt [7:0] $end
$var reg 16 ) starttime [15:0] $end
$var reg 16 * endtime [15:0] $end
$var reg 6 + beginstring [5:0] $end
$var reg 6 , defaultApplVerId [5:0] $end
$var reg 256 - senderCompId [255:0] $end
$var reg 256 . targetCompId [255:0] $end
$var reg 16 / hostAddr [15:0] $end
$var reg 8 0 heartBeatInt [7:0] $end
$var wire 8 1 dout [7:0] $end
$var wire 1 2 valid $end
$var integer 32 3 statusI $end
$var integer 32 4 statusO $end
$var integer 32 5 mon $end
$var reg 8 6 exp [7:0] $end
$var integer 32 7 in $end
$var integer 32 8 out $end
$var integer 32 9 cfg $end
$var integer 32 : dut_error $end

$scope begin unnamed$$_23 $end
$upscope $end


$scope begin unnamed$$_24 $end
$upscope $end


$scope begin unnamed$$_25 $end
$upscope $end


$scope begin unnamed$$_26 $end
$upscope $end


$scope begin unnamed$$_27 $end
$upscope $end


$scope begin unnamed$$_28 $end
$upscope $end


$scope begin unnamed$$_29 $end
$upscope $end


$scope begin unnamed$$_30 $end
$upscope $end


$scope begin unnamed$$_31 $end
$upscope $end


$scope begin unnamed$$_32 $end
$upscope $end


$scope begin unnamed$$_33 $end
$upscope $end


$scope module dut $end
$var wire 1 " clk $end
$var wire 1 ! enable $end
$var wire 1 # reset $end
$var wire 1 % start $end
$var wire 1 $ configure $end
$var wire 8 & din [7:0] $end
$var wire 2 ' connectType [1:0] $end
$var wire 8 ( reconnectInt [7:0] $end
$var wire 16 ) starttime [15:0] $end
$var wire 16 * endtime [15:0] $end
$var wire 6 + beginstring [5:0] $end
$var wire 6 , defaultApplVerId [5:0] $end
$var wire 256 - senderCompId [255:0] $end
$var wire 256 . targetCompId [255:0] $end
$var wire 16 / hostAddr [15:0] $end
$var wire 8 0 heartBeatInt [7:0] $end
$var reg 8 ; dout [7:0] $end
$var reg 1 < valid $end
$upscope $end

$upscope $end

$enddefinitions $end

#0
$dumpvars
0"
x$
x<
0!
x#
x%
x2
bxxxxxx +
b10000000000000000000000000000011 9
bxx '
bxxxxxx ,
b00000000 &
bxxxxxxxx 1
bxxxxxxxx ;
bxxxxxxxxxxxxxxxxxxxxxxxxxxxxxxxx :
bxxxxxxxxxxxxxxxx *
b00000000 6
bxxxxxxxx 0
bxxxxxxxxxxxxxxxx /
b10000000000000000000000000000100 7
b10000000000000000000000000000110 5
b10000000000000000000000000000101 8
bxxxxxxxx (
bxxxxxxxxxxxxxxxxxxxxxxxxxxxxxxxxxxxxxxxxxxxxxxxxxxxxxxxxxxxxxxxxxxxxxxxxxxxxxxxxxxxxxxxxxxxxxxxxxxxxxxxxxxxxxxxxxxxxxxxxxxxxxxxxxxxxxxxxxxxxxxxxxxxxxxxxxxxxxxxxxxxxxxxxxxxxxxxxxxxxxxxxxxxxxxxxxxxxxxxxxxxxxxxxxxxxxxxxxxxxxxxxxxxxxxxxxxxxxxxxxxxxxxxxxxxxxxxx -
bxxxxxxxxxxxxxxxx )
bxxxxxxxxxxxxxxxxxxxxxxxxxxxxxxxx 3
bxxxxxxxxxxxxxxxxxxxxxxxxxxxxxxxx 4
bxxxxxxxxxxxxxxxxxxxxxxxxxxxxxxxxxxxxxxxxxxxxxxxxxxxxxxxxxxxxxxxxxxxxxxxxxxxxxxxxxxxxxxxxxxxxxxxxxxxxxxxxxxxxxxxxxxxxxxxxxxxxxxxxxxxxxxxxxxxxxxxxxxxxxxxxxxxxxxxxxxxxxxxxxxxxxxxxxxxxxxxxxxxxxxxxxxxxxxxxxxxxxxxxxxxxxxxxxxxxxxxxxxxxxxxxxxxxxxxxxxxxxxxxxxxxxxxx .
$end
#10
1"
b00000000 ;
b00000000 1
0<
02
#20
0"
#30
1"
#40
0"
#50
1"
#60
0"
#70
1"
#80
0"
#90
1"
#100
0"
#110
1"
#120
0"
1#
#130
1"
b00000000000000000000000000000000 :
#140
0"
0#
#150
1"
#160
0"
1$
b01 '
b00000000000000000000000000000001 3
b00100000 (
b0000000000000000 )
b0000000000000000 *
b100100 +
b100011 ,
b0000000000000000000000000000000000000000000000000000000000000000000000000000000000000000000000000000000000000000000000000000000000000000000000000000000000000000000000000000000000000000000000000000000000000000000000000000000111111111110000000000011111111111 -
b0000000000000000000000000000000000000000000000000000000000000000000000000000000000000000000000000000000000000000000000000000000000000000000000000000000000000000000000000000000000000000000000000000000000000000000000000000000111111111110000000000011111111111 .
b0000000000000001 /
b00001111 0
#170
1"
#180
0"
0$
#190
1"
#200
0"
#210
1"
#220
0"
#230
1"
#240
0"
#250
1"
#260
0"
#270
1"
#280
0"
#290
1"
#300
0"
#310
1"
#320
0"
1%
#330
1"
#340
0"
0%
#350
1"
#360
0"
1!
b00111000 &
#370
1"
b00111000 ;
b00111000 1
1<
12
#380
0"
0!
#390
1"
b00111000 6
b00000000000000000000000000000001 4
0<
02
#400
0"
1!
b00111101 &
#410
1"
b00111101 ;
b00111101 1
1<
12
#420
0"
0!
#430
1"
b00111101 6
0<
02
#440
0"
1!
b01000110 &
#450
1"
b01000110 ;
b01000110 1
1<
12
#460
0"
0!
#470
1"
b01000110 6
0<
02
#480
0"
1!
b01001001 &
#490
1"
b01001001 ;
b01001001 1
1<
12
#500
0"
0!
#510
1"
b01001001 6
0<
02
#520
0"
1!
b01011000 &
#530
1"
b01011000 ;
b01011000 1
1<
12
#540
0"
0!
#550
1"
b01011000 6
0<
02
#560
0"
1!
b01010100 &
#570
1"
b01010100 ;
b01010100 1
1<
12
#580
0"
0!
#590
1"
b01010100 6
0<
02
#600
0"
1!
b00101110 &
#610
1"
b00101110 ;
b00101110 1
1<
12
#620
0"
0!
#630
1"
b00101110 6
0<
02
#640
0"
1!
b00110001 &
#650
1"
b00110001 ;
b00110001 1
1<
12
#660
0"
0!
#670
1"
b00110001 6
0<
02
#680
0"
1!
b00101110 &
#690
1"
b00101110 ;
b00101110 1
1<
12
#700
0"
0!
#710
1"
b00101110 6
0<
02
#720
0"
1!
b00110001 &
#730
1"
b00110001 ;
b00110001 1
1<
12
#740
0"
0!
#750
1"
b00110001 6
0<
02
#760
0"
1!
b00000001 &
#770
1"
b00000001 ;
b00000001 1
1<
12
#780
0"
0!
#790
1"
b00000001 6
0<
02
#800
0"
1!
b00111001 &
#810
1"
b00111001 ;
b00111001 1
1<
12
#820
0"
0!
#830
1"
b00111001 6
0<
02
#840
0"
1!
b00111101 &
#850
1"
b00111101 ;
b00111101 1
1<
12
#860
0"
0!
#870
1"
b00111101 6
0<
02
#880
0"
1!
b00111000 &
#890
1"
b00111000 ;
b00111000 1
1<
12
#900
0"
0!
#910
1"
b00111000 6
0<
02
#920
0"
1!
b00110000 &
#930
1"
b00110000 ;
b00110000 1
1<
12
#940
0"
0!
#950
1"
b00110000 6
0<
02
#960
0"
1!
b00000001 &
#970
1"
b00000001 ;
b00000001 1
1<
12
#980
0"
0!
#990
1"
b00000001 6
0<
02
#1000
0"
1!
b00110011 &
#1010
1"
b00110011 ;
b00110011 1
1<
12
#1020
0"
0!
#1030
1"
b00110011 6
0<
02
#1040
0"
1!
b00110101 &
#1050
1"
b00110101 ;
b00110101 1
1<
12
#1060
0"
0!
#1070
1"
b00110101 6
0<
02
#1080
0"
1!
b00111101 &
#1090
1"
b00111101 ;
b00111101 1
1<
12
#1100
0"
0!
#1110
1"
b00111101 6
0<
02
#1120
0"
1!
b01000001 &
#1130
1"
b01000001 ;
b01000001 1
1<
12
#1140
0"
0!
#1150
1"
b01000001 6
0<
02
#1160
0"
1!
b00000001 &
#1170
1"
b00000001 ;
b00000001 1
1<
12
#1180
0"
0!
#1190
1"
b00000001 6
0<
02
#1200
0"
1!
b00110011 &
#1210
1"
b00110011 ;
b00110011 1
1<
12
#1220
0"
0!
#1230
1"
b00110011 6
0<
02
#1240
0"
1!
b00110100 &
#1250
1"
b00110100 ;
b00110100 1
1<
12
#1260
0"
0!
#1270
1"
b00110100 6
0<
02
#1280
0"
1!
b00111101 &
#1290
1"
b00111101 ;
b00111101 1
1<
12
#1300
0"
0!
#1310
1"
b00111101 6
0<
02
#1320
0"
1!
b00110010 &
#1330
1"
b00110010 ;
b00110010 1
1<
12
#1340
0"
0!
#1350
1"
b00110010 6
0<
02
#1360
0"
1!
b00110111 &
#1370
1"
b00110111 ;
b00110111 1
1<
12
#1380
0"
0!
#1390
1"
b00110111 6
0<
02
#1400
0"
1!
#1410
1"
1<
12
#1420
0"
0!
#1430
1"
0<
02
#1440
0"
1!
b00000001 &
#1450
1"
b00000001 ;
b00000001 1
1<
12
#1460
0"
0!
#1470
1"
b00000001 6
0<
02
#1480
0"
1!
b00110100 &
#1490
1"
b00110100 ;
b00110100 1
1<
12
#1500
0"
0!
#1510
1"
b00110100 6
0<
02
#1520
0"
1!
b00111001 &
#1530
1"
b00111001 ;
b00111001 1
1<
12
#1540
0"
0!
#1550
1"
b00111001 6
0<
02
#1560
0"
1!
b00111101 &
#1570
1"
b00111101 ;
b00111101 1
1<
12
#1580
0"
0!
#1590
1"
b00111101 6
0<
02
#1600
0"
1!
b01001111 &
#1610
1"
b01001111 ;
b01001111 1
1<
12
#1620
0"
0!
#1630
1"
b01001111 6
0<
02
#1640
0"
1!
b01010010 &
#1650
1"
b01010010 ;
b01010010 1
1<
12
#1660
0"
0!
#1670
1"
b01010010 6
0<
02
#1680
0"
1!
b01000100 &
#1690
1"
b01000100 ;
b01000100 1
1<
12
#1700
0"
0!
#1710
1"
b01000100 6
0<
02
#1720
0"
1!
b01000101 &
#1730
1"
b01000101 ;
b01000101 1
1<
12
#1740
0"
0!
#1750
1"
b01000101 6
0<
02
#1760
0"
1!
b01010010 &
#1770
1"
b01010010 ;
b01010010 1
1<
12
#1780
0"
0!
#1790
1"
b01010010 6
0<
02
#1800
0"
1!
b01001101 &
#1810
1"
b01001101 ;
b01001101 1
1<
12
#1820
0"
0!
#1830
1"
b01001101 6
0<
02
#1840
0"
1!
b01000001 &
#1850
1"
b01000001 ;
b01000001 1
1<
12
#1860
0"
0!
#1870
1"
b01000001 6
0<
02
#1880
0"
1!
b01010100 &
#1890
1"
b01010100 ;
b01010100 1
1<
12
#1900
0"
0!
#1910
1"
b01010100 6
0<
02
#1920
0"
1!
b01000011 &
#1930
1"
b01000011 ;
b01000011 1
1<
12
#1940
0"
0!
#1950
1"
b01000011 6
0<
02
#1960
0"
1!
b01001000 &
#1970
1"
b01001000 ;
b01001000 1
1<
12
#1980
0"
0!
#1990
1"
b01001000 6
0<
02
#2000
0"
1!
b00000001 &
#2010
1"
b00000001 ;
b00000001 1
1<
12
#2020
0"
0!
#2030
1"
b00000001 6
0<
02
#2040
0"
1!
b00110101 &
#2050
1"
b00110101 ;
b00110101 1
1<
12
#2060
0"
0!
#2070
1"
b00110101 6
0<
02
#2080
0"
1!
b00110010 &
#2090
1"
b00110010 ;
b00110010 1
1<
12
#2100
0"
0!
#2110
1"
b00110010 6
0<
02
#2120
0"
1!
b00111101 &
#2130
1"
b00111101 ;
b00111101 1
1<
12
#2140
0"
0!
#2150
1"
b00111101 6
0<
02
#2160
0"
1!
b00110010 &
#2170
1"
b00110010 ;
b00110010 1
1<
12
#2180
0"
0!
#2190
1"
b00110010 6
0<
02
#2200
0"
1!
b00110000 &
#2210
1"
b00110000 ;
b00110000 1
1<
12
#2220
0"
0!
#2230
1"
b00110000 6
0<
02
#2240
0"
1!
b00110001 &
#2250
1"
b00110001 ;
b00110001 1
1<
12
#2260
0"
0!
#2270
1"
b00110001 6
0<
02
#2280
0"
1!
b00110011 &
#2290
1"
b00110011 ;
b00110011 1
1<
12
#2300
0"
0!
#2310
1"
b00110011 6
0<
02
#2320
0"
1!
b00110000 &
#2330
1"
b00110000 ;
b00110000 1
1<
12
#2340
0"
0!
#2350
1"
b00110000 6
0<
02
#2360
0"
1!
b00110011 &
#2370
1"
b00110011 ;
b00110011 1
1<
12
#2380
0"
0!
#2390
1"
b00110011 6
0<
02
#2400
0"
1!
#2410
1"
1<
12
#2420
0"
0!
#2430
1"
0<
02
#2440
0"
1!
b00110000 &
#2450
1"
b00110000 ;
b00110000 1
1<
12
#2460
0"
0!
#2470
1"
b00110000 6
0<
02
#2480
0"
1!
b00101101 &
#2490
1"
b00101101 ;
b00101101 1
1<
12
#2500
0"
0!
#2510
1"
b00101101 6
0<
02
#2520
0"
1!
b00110001 &
#2530
1"
b00110001 ;
b00110001 1
1<
12
#2540
0"
0!
#2550
1"
b00110001 6
0<
02
#2560
0"
1!
b00110111 &
#2570
1"
b00110111 ;
b00110111 1
1<
12
#2580
0"
0!
#2590
1"
b00110111 6
0<
02
#2600
0"
1!
b00111010 &
#2610
1"
b00111010 ;
b00111010 1
1<
12
#2620
0"
0!
#2630
1"
b00111010 6
0<
02
#2640
0"
1!
b00110000 &
#2650
1"
b00110000 ;
b00110000 1
1<
12
#2660
0"
0!
#2670
1"
b00110000 6
0<
02
#2680
0"
1!
b00110101 &
#2690
1"
b00110101 ;
b00110101 1
1<
12
#2700
0"
0!
#2710
1"
b00110101 6
0<
02
#2720
0"
1!
b00111010 &
#2730
1"
b00111010 ;
b00111010 1
1<
12
#2740
0"
0!
#2750
1"
b00111010 6
0<
02
#2760
0"
1!
b00110011 &
#2770
1"
b00110011 ;
b00110011 1
1<
12
#2780
0"
0!
#2790
1"
b00110011 6
0<
02
#2800
0"
1!
b00110010 &
#2810
1"
b00110010 ;
b00110010 1
1<
12
#2820
0"
0!
#2830
1"
b00110010 6
0<
02
#2840
0"
1!
b00101110 &
#2850
1"
b00101110 ;
b00101110 1
1<
12
#2860
0"
0!
#2870
1"
b00101110 6
0<
02
#2880
0"
1!
b00110011 &
#2890
1"
b00110011 ;
b00110011 1
1<
12
#2900
0"
0!
#2910
1"
b00110011 6
0<
02
#2920
0"
1!
b00110100 &
#2930
1"
b00110100 ;
b00110100 1
1<
12
#2940
0"
0!
#2950
1"
b00110100 6
0<
02
#2960
0"
1!
b00110001 &
#2970
1"
b00110001 ;
b00110001 1
1<
12
#2980
0"
0!
#2990
1"
b00110001 6
0<
02
#3000
0"
1!
b00000001 &
#3010
1"
b00000001 ;
b00000001 1
1<
12
#3020
0"
0!
#3030
1"
b00000001 6
0<
02
#3040
0"
1!
b00110101 &
#3050
1"
b00110101 ;
b00110101 1
1<
12
#3060
0"
0!
#3070
1"
b00110101 6
0<
02
#3080
0"
1!
b00110110 &
#3090
1"
b00110110 ;
b00110110 1
1<
12
#3100
0"
0!
#3110
1"
b00110110 6
0<
02
#3120
0"
1!
b00111101 &
#3130
1"
b00111101 ;
b00111101 1
1<
12
#3140
0"
0!
#3150
1"
b00111101 6
0<
02
#3160
0"
1!
b01000011 &
#3170
1"
b01000011 ;
b01000011 1
1<
12
#3180
0"
0!
#3190
1"
b01000011 6
0<
02
#3200
0"
1!
b01001100 &
#3210
1"
b01001100 ;
b01001100 1
1<
12
#3220
0"
0!
#3230
1"
b01001100 6
0<
02
#3240
0"
1!
b01001001 &
#3250
1"
b01001001 ;
b01001001 1
1<
12
#3260
0"
0!
#3270
1"
b01001001 6
0<
02
#3280
0"
1!
b01000101 &
#3290
1"
b01000101 ;
b01000101 1
1<
12
#3300
0"
0!
#3310
1"
b01000101 6
0<
02
#3320
0"
1!
b01001110 &
#3330
1"
b01001110 ;
b01001110 1
1<
12
#3340
0"
0!
#3350
1"
b01001110 6
0<
02
#3360
0"
1!
b01010100 &
#3370
1"
b01010100 ;
b01010100 1
1<
12
#3380
0"
0!
#3390
1"
b01010100 6
0<
02
#3400
0"
1!
b00110001 &
#3410
1"
b00110001 ;
b00110001 1
1<
12
#3420
0"
0!
#3430
1"
b00110001 6
0<
02
#3440
0"
1!
b00000001 &
#3450
1"
b00000001 ;
b00000001 1
1<
12
#3460
0"
0!
#3470
1"
b00000001 6
0<
02
#3480
0"
1!
b00111001 &
#3490
1"
b00111001 ;
b00111001 1
1<
12
#3500
0"
0!
#3510
1"
b00111001 6
0<
02
#3520
0"
1!
b00111000 &
#3530
1"
b00111000 ;
b00111000 1
1<
12
#3540
0"
0!
#3550
1"
b00111000 6
0<
02
#3560
0"
1!
b00111101 &
#3570
1"
b00111101 ;
b00111101 1
1<
12
#3580
0"
0!
#3590
1"
b00111101 6
0<
02
#3600
0"
1!
b00110000 &
#3610
1"
b00110000 ;
b00110000 1
1<
12
#3620
0"
0!
#3630
1"
b00110000 6
0<
02
#3640
0"
1!
b00000001 &
#3650
1"
b00000001 ;
b00000001 1
1<
12
#3660
0"
0!
#3670
1"
b00000001 6
0<
02
#3680
0"
1!
b00110001 &
#3690
1"
b00110001 ;
b00110001 1
1<
12
#3700
0"
0!
#3710
1"
b00110001 6
0<
02
#3720
0"
1!
b00110000 &
#3730
1"
b00110000 ;
b00110000 1
1<
12
#3740
0"
0!
#3750
1"
b00110000 6
0<
02
#3760
0"
1!
b00111000 &
#3770
1"
b00111000 ;
b00111000 1
1<
12
#3780
0"
0!
#3790
1"
b00111000 6
0<
02
#3800
0"
1!
b00111101 &
#3810
1"
b00111101 ;
b00111101 1
1<
12
#3820
0"
0!
#3830
1"
b00111101 6
0<
02
#3840
0"
1!
b00110101 &
#3850
1"
b00110101 ;
b00110101 1
1<
12
#3860
0"
0!
#3870
1"
b00110101 6
0<
02
#3880
0"
1!
b00000001 &
#3890
1"
b00000001 ;
b00000001 1
1<
12
#3900
0"
0!
#3910
1"
b00000001 6
0<
02
#3920
0"
1!
b00110001 &
#3930
1"
b00110001 ;
b00110001 1
1<
12
#3940
0"
0!
#3950
1"
b00110001 6
0<
02
#3960
0"
1!
#3970
1"
1<
12
#3980
0"
0!
#3990
1"
0<
02
#4000
0"
1!
b00110011 &
#4010
1"
b00110011 ;
b00110011 1
1<
12
#4020
0"
0!
#4030
1"
b00110011 6
0<
02
#4040
0"
1!
b00110111 &
#4050
1"
b00110111 ;
b00110111 1
1<
12
#4060
0"
0!
#4070
1"
b00110111 6
0<
02
#4080
0"
1!
b00111101 &
#4090
1"
b00111101 ;
b00111101 1
1<
12
#4100
0"
0!
#4110
1"
b00111101 6
0<
02
#4120
0"
1!
b00110111 &
#4130
1"
b00110111 ;
b00110111 1
1<
12
#4140
0"
0!
#4150
1"
b00110111 6
0<
02
#4160
0"
1!
b00000001 &
#4170
1"
b00000001 ;
b00000001 1
1<
12
#4180
0"
0!
#4190
1"
b00000001 6
0<
02
#4200
0"
1!
b00110001 &
#4210
1"
b00110001 ;
b00110001 1
1<
12
#4220
0"
0!
#4230
1"
b00110001 6
0<
02
#4240
0"
1!
b00110000 &
#4250
1"
b00110000 ;
b00110000 1
1<
12
#4260
0"
0!
#4270
1"
b00110000 6
0<
02
#4280
0"
1!
b00111101 &
#4290
1"
b00111101 ;
b00111101 1
1<
12
#4300
0"
0!
#4310
1"
b00111101 6
0<
02
#4320
0"
1!
b00110001 &
#4330
1"
b00110001 ;
b00110001 1
1<
12
#4340
0"
0!
#4350
1"
b00110001 6
0<
02
#4360
0"
1!
b00110101 &
#4370
1"
b00110101 ;
b00110101 1
1<
12
#4380
0"
0!
#4390
1"
b00110101 6
0<
02
#4400
0"
1!
b00110111 &
#4410
1"
b00110111 ;
b00110111 1
1<
12
#4420
0"
0!
#4430
1"
b00110111 6
0<
02
#4440
0"
1!
b00000001 &
#4450
1"
b00000001 ;
b00000001 1
1<
12
#4460
0"
0!
#4470
1"
b00000001 6
0<
02
#4480
0"
1!
b00111011 &
#4490
1"
b00111011 ;
b00111011 1
1<
12
#4500
0"
0!
#4510
1"
b00111011 6
0<
02
#4520
0"
#4530
1"
#4540
0"
#4550
1"
#4560
0"
#4570
1"
#4580
0"
#4590
1"
#4600
0"
1!
b00111000 &
#4610
1"
b00111000 ;
b00111000 1
1<
12
#4620
0"
0!
#4630
1"
b00111000 6
0<
02
#4640
0"
1!
b00111101 &
#4650
1"
b00111101 ;
b00111101 1
1<
12
#4660
0"
0!
#4670
1"
b00111101 6
0<
02
#4680
0"
1!
b01000110 &
#4690
1"
b01000110 ;
b01000110 1
1<
12
#4700
0"
0!
#4710
1"
b01000110 6
0<
02
#4720
0"
1!
b01001001 &
#4730
1"
b01001001 ;
b01001001 1
1<
12
#4740
0"
0!
#4750
1"
b01001001 6
0<
02
#4760
0"
1!
b01011000 &
#4770
1"
b01011000 ;
b01011000 1
1<
12
#4780
0"
0!
#4790
1"
b01011000 6
0<
02
#4800
0"
1!
b01010100 &
#4810
1"
b01010100 ;
b01010100 1
1<
12
#4820
0"
0!
#4830
1"
b01010100 6
0<
02
#4840
0"
1!
b00101110 &
#4850
1"
b00101110 ;
b00101110 1
1<
12
#4860
0"
0!
#4870
1"
b00101110 6
0<
02
#4880
0"
1!
b00110001 &
#4890
1"
b00110001 ;
b00110001 1
1<
12
#4900
0"
0!
#4910
1"
b00110001 6
0<
02
#4920
0"
1!
b00101110 &
#4930
1"
b00101110 ;
b00101110 1
1<
12
#4940
0"
0!
#4950
1"
b00101110 6
0<
02
#4960
0"
1!
b00110001 &
#4970
1"
b00110001 ;
b00110001 1
1<
12
#4980
0"
0!
#4990
1"
b00110001 6
0<
02
#5000
0"
1!
b00000001 &
#5010
1"
b00000001 ;
b00000001 1
1<
12
#5020
0"
0!
#5030
1"
b00000001 6
0<
02
#5040
0"
1!
b00111001 &
#5050
1"
b00111001 ;
b00111001 1
1<
12
#5060
0"
0!
#5070
1"
b00111001 6
0<
02
#5080
0"
1!
b00111101 &
#5090
1"
b00111101 ;
b00111101 1
1<
12
#5100
0"
0!
#5110
1"
b00111101 6
0<
02
#5120
0"
1!
b00110110 &
#5130
1"
b00110110 ;
b00110110 1
1<
12
#5140
0"
0!
#5150
1"
b00110110 6
0<
02
#5160
0"
1!
b00110010 &
#5170
1"
b00110010 ;
b00110010 1
1<
12
#5180
0"
0!
#5190
1"
b00110010 6
0<
02
#5200
0"
1!
b00000001 &
#5210
1"
b00000001 ;
b00000001 1
1<
12
#5220
0"
0!
#5230
1"
b00000001 6
0<
02
#5240
0"
1!
b00110011 &
#5250
1"
b00110011 ;
b00110011 1
1<
12
#5260
0"
0!
#5270
1"
b00110011 6
0<
02
#5280
0"
1!
b00110101 &
#5290
1"
b00110101 ;
b00110101 1
1<
12
#5300
0"
0!
#5310
1"
b00110101 6
0<
02
#5320
0"
1!
b00111101 &
#5330
1"
b00111101 ;
b00111101 1
1<
12
#5340
0"
0!
#5350
1"
b00111101 6
0<
02
#5360
0"
1!
b00110000 &
#5370
1"
b00110000 ;
b00110000 1
1<
12
#5380
0"
0!
#5390
1"
b00110000 6
0<
02
#5400
0"
1!
b00000001 &
#5410
1"
b00000001 ;
b00000001 1
1<
12
#5420
0"
0!
#5430
1"
b00000001 6
0<
02
#5440
0"
1!
b00110011 &
