bin2bcd/binary_to_bcd.v
module binary_to_bcd (
  clk_i,
  ce_i,
  rst_i,
  start_i,
  dat_binary_i,
  dat_bcd_o,
  done_o,

  ascii_o,
  size_o,
  width_o
  );

parameter BITS_IN_PP         = 32; // # of bits of binary input
parameter BCD_DIGITS_OUT_PP  = 10;  // # of digits of BCD output
parameter BIT_COUNT_WIDTH_PP = 5;  // Width of bit counter
 
// I/O declarations
input  clk_i;                      // clock signal
input  ce_i;                       // clock enable input
input  rst_i;                      // synchronous reset
input  start_i;                    // initiates a conversion
input  [BITS_IN_PP-1:0] dat_binary_i;        // input bus
output [4*BCD_DIGITS_OUT_PP-1:0] dat_bcd_o;  // output bus
output done_o;                     // indicates conversion is done
output [3:0]	width_o;
 
reg [4*BCD_DIGITS_OUT_PP-1:0] dat_bcd_o;
integer			i;
reg [8*BCD_DIGITS_OUT_PP-1:0] ascii;
output [8*BCD_DIGITS_OUT_PP-1:0] ascii_o;
reg [9:0] size;
output [9:0] size_o;

 
reg [3:0]	width;
//reg [4:0] 	bit_width;
reg [9:0] 	bit_width;			// edit ams


// Internal signal declarations
 
reg  [BITS_IN_PP-1:0] bin_reg;
reg  [4*BCD_DIGITS_OUT_PP-1:0] bcd_reg;
wire [BITS_IN_PP-1:0] bin_next;
reg  [4*BCD_DIGITS_OUT_PP-1:0] bcd_next;
reg  busy_bit;
reg  [BIT_COUNT_WIDTH_PP-1:0] bit_count;
wire bit_count_done;
 
//--------------------------------------------------------------------------
// Functions & Tasks
//--------------------------------------------------------------------------
 
function [4*BCD_DIGITS_OUT_PP-1:0] bcd_asl;
  input [4*BCD_DIGITS_OUT_PP-1:0] din;
  input newbit;
  integer k;
  reg cin;
  reg [3:0] digit;
  reg [3:0] digit_less;
  begin
    cin = newbit;
    for (k=0; k<BCD_DIGITS_OUT_PP; k=k+1)
    begin
      digit[3] = din[4*k+3];
      digit[2] = din[4*k+2];
      digit[1] = din[4*k+1];
      digit[0] = din[4*k];
      digit_less = digit - 5;
      if (digit > 4'b0100)
      begin
        bcd_asl[4*k+3] = digit_less[2];
        bcd_asl[4*k+2] = digit_less[1];
        bcd_asl[4*k+1] = digit_less[0];
        bcd_asl[4*k+0] = cin;
        cin = 1'b1;
      end
      else
      begin
        bcd_asl[4*k+3] = digit[2];
        bcd_asl[4*k+2] = digit[1];
        bcd_asl[4*k+1] = digit[0];
        bcd_asl[4*k+0] = cin;
        cin = 1'b0;
      end
 
    end // end of for loop
  end
endfunction
 
//--------------------------------------------------------------------------
// Module code
//--------------------------------------------------------------------------
 
// Perform proper shifting, binary ASL and BCD ASL
assign bin_next = {bin_reg,1'b0};
always @(bcd_reg or bin_reg)
begin
  bcd_next <= bcd_asl(bcd_reg,bin_reg[BITS_IN_PP-1]);
end
 
// Busy bit, input and output registers
always @(posedge clk_i)
begin
  if (rst_i)
  begin
    busy_bit <= 0;  // Synchronous reset
    dat_bcd_o <= 0;
  end
  else if (start_i && ~busy_bit)
  begin
    busy_bit <= 1;
    bin_reg <= dat_binary_i;
    bcd_reg <= 0;
  end
  else if (busy_bit && ce_i && bit_count_done && ~start_i)
  begin
    busy_bit <= 0;
    dat_bcd_o <= bcd_next;
  end
  else if (busy_bit && ce_i && ~bit_count_done)
  begin
    bcd_reg <= bcd_next;
    bin_reg <= bin_next;
  end
end
assign done_o = ~busy_bit;
 
// Bit counter
always @(posedge clk_i)
begin
  if (~busy_bit) bit_count <= 0;
  else if (ce_i && ~bit_count_done) bit_count <= bit_count + 1;
end
assign bit_count_done = (bit_count == (BITS_IN_PP-1));

always @(*) begin

bit_width[0] = ~ (bcd_next[0] | bcd_next[1] | bcd_next[2] | bcd_next[3]); 
bit_width[1] = ~ (bcd_next[4] | bcd_next[5] | bcd_next[6] | bcd_next[7]); 
bit_width[2] = ~ (bcd_next[8] | bcd_next[9] | bcd_next[10] | bcd_next[11]); 
bit_width[3] = ~ (bcd_next[12] | bcd_next[13] | bcd_next[14] | bcd_next[15]); 
bit_width[4] = ~ (bcd_next[16] | bcd_next[17] | bcd_next[18] | bcd_next[19]); 
bit_width[5] = ~ (bcd_next[20] | bcd_next[21] | bcd_next[22] | bcd_next[23]); 
bit_width[6] = ~ (bcd_next[24] | bcd_next[25] | bcd_next[26] | bcd_next[27]); 
bit_width[7] = ~ (bcd_next[28] | bcd_next[29] | bcd_next[30] | bcd_next[31]); 
bit_width[8] = ~ (bcd_next[32] | bcd_next[33] | bcd_next[34] | bcd_next[35]); 
bit_width[9] = ~ (bcd_next[36] | bcd_next[37] | bcd_next[38] | bcd_next[39]); 

	for (i = 0; i < 10; i++) begin
		case (bcd_next[i*4 +: 4])
			4'b0000	: ascii[i*8 +: 8]		=	8'b00110000;
			4'b0001	: ascii[i*8 +: 8]		=	8'b00110001;
			4'b0010	: ascii[i*8 +: 8]		=	8'b00110010;
			4'b0011	: ascii[i*8 +: 8]		=	8'b00110011;
			4'b0100	: ascii[i*8 +: 8]		=	8'b00110100;
			4'b0101	: ascii[i*8 +: 8]		=	8'b00110101;
			4'b0110	: ascii[i*8 +: 8]		=	8'b00110110;
			4'b0111	: ascii[i*8 +: 8]		=	8'b00110111;
			4'b1000	: ascii[i*8 +: 8]		=	8'b00111000;
			4'b1001	: ascii[i*8 +: 8]		=	8'b00111001;
			default	: ascii[i*8 +: 8]		=	'0;		
		endcase
	end


	casez (bit_width) 
		10'b0????????? : begin width = 4'b1010; size = 10'b1111111111; end
		10'b10???????? : begin width = 4'b1001; size = 10'b0111111111; end
		10'b110??????? : begin width = 4'b1000; size = 10'b0011111111; end
		10'b1110?????? : begin width = 4'b0111; size = 10'b0001111111; end
		10'b11110????? : begin width = 4'b0110; size = 10'b0000111111; end
		10'b111110???? : begin width = 4'b0101; size = 10'b0000011111; end
		10'b1111110??? : begin width = 4'b0100; size = 10'b0000001111; end
		10'b11111110?? : begin width = 4'b0011; size = 10'b0000000111; end
		10'b111111110? : begin width = 4'b0010; size = 10'b0000000011; end
		10'b1111111110 : begin width = 4'b0001; size = 10'b0000000001; end
		10'b1111111111 : begin width = 4'b0000; size = '0; end
		default  : begin width = 4'b0000; size = '0; end
	endcase
end

assign width_o	=	width;
assign size_o	=	size;
assign ascii_o	=	ascii;
 
endmodule

bin2bcd/dut.v
/**
 * @filename		dut.sv 
 *
 * @brief     	        A simple testbench. 	
 *
 * @author		Adil Sadik <sadik.adil@gmail.com> 
 */

module test();

	
	reg	 	clk_i;
	reg	 	ce_i;
	reg	 	rst_i;
	reg		start_i;
	reg[31:0]	dat_binary_i;
	reg[39:0]	dat_bcd_o;
	reg		done_o;
	reg[79:0]	ascii_o;
	reg[9:0]	size_o;
	reg[3:0]	width_o;


binary_to_bcd bin2bcd (.clk_i, .ce_i, .rst_i, .start_i, .dat_binary_i, .dat_bcd_o, .done_o, .ascii_o, .size_o, .width_o);


initial begin

int veriable;
int stop;

$vcdpluson;

#1 clk_i = 0;
#1 clk_i = 1;
start_i = 0;
//dat_binary_i = 16'b0000000000001111;
rst_i = 1;
ce_i = 1;
#1 clk_i = 0;
#1 clk_i = 1;

rst_i = 0;
#1 clk_i = 0;
#1 clk_i = 1;

#1 clk_i = 0;
#1 clk_i = 1;

ce_i = 1;
rst_i = 0;
//dat_binary_i = 16'b1111111111111111;
//dat_binary_i = 16'b0000000000010000;

dat_binary_i = {31'b0, 1'b1};

start_i = 1;


#1 clk_i = 0;
#1 clk_i = 1;

start_i = 0;

#1 clk_i = 0;
#1 clk_i = 1;


#1 clk_i = 0;
#1 clk_i = 1;

//rst_i = 1;
 veriable = 0;
 stop = 1000;

while (veriable <stop) begin

#1 clk_i = 0;
#1 clk_i = 1;

veriable = veriable+1;
end

end

endmodule

bin2bcd/waveform.vcd
$timescale
 1s
$end

$scope module test $end
$var reg        1 "    clk_i $end
$var reg        1 #    ce_i $end
$var reg        1 $    rst_i $end
$var reg        1 %    start_i $end
$var reg       32 &    dat_binary_i [31:0] $end
$var reg       40 '    dat_bcd_o [39:0] $end
$var reg        1 (    done_o $end
$var reg       80 )    ascii_o [79:0] $end
$var reg       10 *    size_o [9:0] $end
$var reg        4 +    width_o [3:0] $end

$scope begin unnamed$$_0 $end
$var integer   32 ,    veriable [31:0] $end
$var integer   32 -    stop [31:0] $end
$upscope $end

$scope module bin2bcd $end
$var wire       1 "    clk_i $end
$var wire       1 #    ce_i $end
$var wire       1 $    rst_i $end
$var wire       1 %    start_i $end
$var wire      32 &    dat_binary_i [31:0] $end
$var reg       40 '    dat_bcd_o [39:0] $end
$var wire       1 .    done_o $end
$var wire       4 /    width_o [3:0] $end
$var integer   32 0    i $end
$var reg       80 1    ascii [79:0] $end
$var wire      80 2    ascii_o [79:0] $end
$var reg       10 3    size [9:0] $end
$var wire      10 4    size_o [9:0] $end
$var reg        4 5    width [3:0] $end
$var reg       10 6    bit_width [9:0] $end
$var reg       32 7    bin_reg [31:0] $end
$var reg       40 8    bcd_reg [39:0] $end
$var wire      32 9    bin_next [31:0] $end
$var reg       40 :    bcd_next [39:0] $end
$var reg        1 ;    busy_bit $end
$var reg        5 <    bit_count [4:0] $end
$var wire       1 =    bit_count_done $end
$var parameter  32 >    BITS_IN_PP [31:0] $end
$var parameter  32 ?    BCD_DIGITS_OUT_PP [31:0] $end
$var parameter  32 @    BIT_COUNT_WIDTH_PP [31:0] $end

$scope function bcd_asl $end
$var reg       40 A    bcd_asl [39:0] $end
$var reg       40 B    din [39:0] $end
$var reg        1 C    newbit $end
$var integer   32 D    k $end
$var reg        1 E    cin $end
$var reg        4 F    digit [3:0] $end
$var reg        4 G    digit_less [3:0] $end
$upscope $end
$upscope $end
$upscope $end
$enddefinitions $end
#0
$dumpvars
bxxxxxxxxxxxxxxxxxxxxxxxxxxxxxxxxxxxxxxxx A
bxxxxxxxxxx 6
bxxxx +
bxxxxxxxxxxxxxxxxxxxxxxxxxxxxxxxxxxxxxxxx B
bxxxxxxxxxxxxxxxxxxxxxxxxxxxxxxxx 7
b00000000000000000000000000000000 ,
xC
bxxxxxxxxxxxxxxxxxxxxxxxxxxxxxxxxxxxxxxxx 8
b00000000000000000000000000000000 -
x"
bxxxxxxxxxxxxxxxxxxxxxxxxxxxxxxxx D
bxxxxxxxxxxxxxxxxxxxxxxxxxxxxxxx0 9
x.
x#
xE
bxxxxxxxxxxxxxxxxxxxxxxxxxxxxxxxxxxxxxxxx :
bxxxx /
x$
bxxxx F
x;
bxxxxxxxxxxxxxxxxxxxxxxxxxxxxxxxx 0
x%
bxxxx G
bxxxxx <
bxxxxxxxxxxxxxxxxxxxxxxxxxxxxxxxxxxxxxxxxxxxxxxxxxxxxxxxxxxxxxxxxxxxxxxxxxxxxxxxx 1
bxxxxxxxxxxxxxxxxxxxxxxxxxxxxxxxx &
x=
bxxxxxxxxxxxxxxxxxxxxxxxxxxxxxxxxxxxxxxxxxxxxxxxxxxxxxxxxxxxxxxxxxxxxxxxxxxxxxxxx 2
bxxxxxxxxxxxxxxxxxxxxxxxxxxxxxxxxxxxxxxxx '
b00000000000000000000000000100000 >
bxxxxxxxxxx 3
x(
b00000000000000000000000000001010 ?
bxxxxxxxxxx 4
bxxxxxxxxxxxxxxxxxxxxxxxxxxxxxxxxxxxxxxxxxxxxxxxxxxxxxxxxxxxxxxxxxxxxxxxxxxxxxxxx )
b00000000000000000000000000000101 @
bxxxx 5
bxxxxxxxxxx *
$end
#1
0"
#2
1.
1#
1$
0;
0%
b0000000000000000000000000000000000000000 '
1(
1"
#3
0"
#4
b00000 <
0=
0$
1"
#5
0"
#6
1"
#7
0"
#8
b0000000000000000000000000000000000000000 A
b1111111111 6
b0000 +
b0000000000000000000000000000000000000000 B
b00000000000000000000000000000001 7
0C
b0000000000000000000000000000000000000000 8
b00000000000000000000000000001010 D
b00000000000000000000000000000010 9
0E
b0000000000000000000000000000000000000000 :
b0000 /
b0000 F
b00000000000000000000000000001010 0
b1011 G
b00110000001100000011000000110000001100000011000000110000001100000011000000110000 1
b00000000000000000000000000000001 &
b00110000001100000011000000110000001100000011000000110000001100000011000000110000 2
b0000000000 3
b0000000000 4
b00110000001100000011000000110000001100000011000000110000001100000011000000110000 )
b0000 5
b0000000000 *
0.
1;
1%
0(
1"
#9
0"
#10
b00001 <
b00000000000000000000000000000010 7
b00000000000000000000000000000100 9
0%
1"
#11
0"
#12
b00010 <
b00000000000000000000000000000100 7
b00000000000000000000000000001000 9
1"
#13
0"
#14
b00000000000000000000001111101000 -
b00011 <
b00000000000000000000000000001000 7
b00000000000000000000000000010000 9
1"
#15
0"
#16
b00000000000000000000000000000001 ,
b00100 <
b00000000000000000000000000010000 7
b00000000000000000000000000100000 9
1"
#17
0"
#18
b00000000000000000000000000000010 ,
b00101 <
b00000000000000000000000000100000 7
b00000000000000000000000001000000 9
1"
#19
0"
#20
b00000000000000000000000000000011 ,
b00110 <
b00000000000000000000000001000000 7
b00000000000000000000000010000000 9
1"
#21
0"
#22
b00000000000000000000000000000100 ,
b00111 <
b00000000000000000000000010000000 7
b00000000000000000000000100000000 9
1"
#23
0"
#24
b00000000000000000000000000000101 ,
b01000 <
b00000000000000000000000100000000 7
b00000000000000000000001000000000 9
1"
#25
0"
#26
b00000000000000000000000000000110 ,
b01001 <
b00000000000000000000001000000000 7
b00000000000000000000010000000000 9
1"
#27
0"
#28
b00000000000000000000000000000111 ,
b01010 <
b00000000000000000000010000000000 7
b00000000000000000000100000000000 9
1"
#29
0"
#30
b00000000000000000000000000001000 ,
b01011 <
b00000000000000000000100000000000 7
b00000000000000000001000000000000 9
1"
#31
0"
#32
b00000000000000000000000000001001 ,
b01100 <
b00000000000000000001000000000000 7
b00000000000000000010000000000000 9
1"
#33
0"
#34
b00000000000000000000000000001010 ,
b01101 <
b00000000000000000010000000000000 7
b00000000000000000100000000000000 9
1"
#35
0"
#36
b00000000000000000000000000001011 ,
b01110 <
b00000000000000000100000000000000 7
b00000000000000001000000000000000 9
1"
#37
0"
#38
b00000000000000000000000000001100 ,
b01111 <
b00000000000000001000000000000000 7
b00000000000000010000000000000000 9
1"
#39
0"
#40
b00000000000000000000000000001101 ,
b10000 <
b00000000000000010000000000000000 7
b00000000000000100000000000000000 9
1"
#41
0"
#42
b00000000000000000000000000001110 ,
b10001 <
b00000000000000100000000000000000 7
b00000000000001000000000000000000 9
1"
#43
0"
#44
b00000000000000000000000000001111 ,
b10010 <
b00000000000001000000000000000000 7
b00000000000010000000000000000000 9
1"
#45
0"
#46
b00000000000000000000000000010000 ,
b10011 <
b00000000000010000000000000000000 7
b00000000000100000000000000000000 9
1"
#47
0"
#48
b00000000000000000000000000010001 ,
b10100 <
b00000000000100000000000000000000 7
b00000000001000000000000000000000 9
1"
#49
0"
#50
b00000000000000000000000000010010 ,
b10101 <
b00000000001000000000000000000000 7
b00000000010000000000000000000000 9
1"
#51
0"
#52
b00000000000000000000000000010011 ,
b10110 <
b00000000010000000000000000000000 7
b00000000100000000000000000000000 9
1"
#53
0"
#54
b00000000000000000000000000010100 ,
b10111 <
b00000000100000000000000000000000 7
b00000001000000000000000000000000 9
1"
#55
0"
#56
b00000000000000000000000000010101 ,
b11000 <
b00000001000000000000000000000000 7
b00000010000000000000000000000000 9
1"
#57
0"
#58
b00000000000000000000000000010110 ,
b11001 <
b00000010000000000000000000000000 7
b00000100000000000000000000000000 9
1"
#59
0"
#60
b00000000000000000000000000010111 ,
b11010 <
b00000100000000000000000000000000 7
b00001000000000000000000000000000 9
1"
#61
0"
#62
b00000000000000000000000000011000 ,
b11011 <
b00001000000000000000000000000000 7
b00010000000000000000000000000000 9
1"
#63
0"
#64
b00000000000000000000000000011001 ,
b11100 <
b00010000000000000000000000000000 7
b00100000000000000000000000000000 9
1"
#65
0"
#66
b00000000000000000000000000011010 ,
b11101 <
b00100000000000000000000000000000 7
b01000000000000000000000000000000 9
1"
#67
0"
#68
b00000000000000000000000000011011 ,
b11110 <
b01000000000000000000000000000000 7
b10000000000000000000000000000000 9
1"
#69
0"
#70
1=
b0000000000000000000000000000000000000001 A
b1111111110 6
b0001 +
1C
b0000000000000000000000000000000000000001 :
b0001 /
b00110000001100000011000000110000001100000011000000110000001100000011000000110001 1
b00110000001100000011000000110000001100000011000000110000001100000011000000110001 2
b0000000001 3
b0000000001 4
b00110000001100000011000000110000001100000011000000110000001100000011000000110001 )
b0001 5
b0000000001 *
b00000000000000000000000000011100 ,
b11111 <
b10000000000000000000000000000000 7
b00000000000000000000000000000000 9
1"
#71
0"
#72
b0000000000000000000000000000000000000001 '
1.
0;
1(
b00000000000000000000000000011101 ,
1"
#73
0"
#74
0=
b00000 <
b00000000000000000000000000011110 ,
1"
#75
0"
#76
b00000000000000000000000000011111 ,
1"
#77
0"
#78
b00000000000000000000000000100000 ,
1"
#79
0"
#80
b00000000000000000000000000100001 ,
1"
#81
0"
#82
b00000000000000000000000000100010 ,
1"
#83
0"
#84
b00000000000000000000000000100011 ,
1"
#85
0"
#86
b00000000000000000000000000100100 ,
1"
#87
0"
#88
b00000000000000000000000000100101 ,
1"
#89
0"
#90
b00000000000000000000000000100110 ,
1"
#91
0"
#92
b00000000000000000000000000100111 ,
1"
#93
0"
#94
b00000000000000000000000000101000 ,
1"
#95
0"
#96
b00000000000000000000000000101001 ,
1"
#97
0"
#98
b00000000000000000000000000101010 ,
1"
#99
0"
#100
b00000000000000000000000000101011 ,
1"
#101
0"
#102
b00000000000000000000000000101100 ,
1"
#103
0"
#104
b00000000000000000000000000101101 ,
1"
#105
0"
#106
b00000000000000000000000000101110 ,
1"
#107
0"
#108
b00000000000000000000000000101111 ,
1"
#109
0"
#110
b00000000000000000000000000110000 ,
1"
#111
0"
#112
b00000000000000000000000000110001 ,
1"
#113
0"
#114
b00000000000000000000000000110010 ,
1"
#115
0"
#116
b00000000000000000000000000110011 ,
1"
#117
0"
#118
b00000000000000000000000000110100 ,
1"
#119
0"
#120
b00000000000000000000000000110101 ,
1"
#121
0"
#122
b00000000000000000000000000110110 ,
1"
#123
0"
#124
b00000000000000000000000000110111 ,
1"
#125
0"
#126
b00000000000000000000000000111000 ,
1"
#127
0"
#128
b00000000000000000000000000111001 ,
1"
#129
0"
#130
b00000000000000000000000000111010 ,
1"
#131
0"
#132
b00000000000000000000000000111011 ,
1"
#133
0"
#134
b00000000000000000000000000111100 ,
1"
#135
0"
#136
b00000000000000000000000000111101 ,
1"
#137
0"
#138
b00000000000000000000000000111110 ,
1"
#139
0"
#140
b00000000000000000000000000111111 ,
1"
#141
0"
#142
b00000000000000000000000001000000 ,
1"
#143
0"
#144
b00000000000000000000000001000001 ,
1"
#145
0"
#146
b00000000000000000000000001000010 ,
1"
#147
0"
#148
b00000000000000000000000001000011 ,
1"
#149
0"
#150
b00000000000000000000000001000100 ,
1"
#151
0"
#152
b00000000000000000000000001000101 ,
1"
#153
0"
#154
b00000000000000000000000001000110 ,
1"
#155
0"
#156
b00000000000000000000000001000111 ,
1"
#157
0"
#158
b00000000000000000000000001001000 ,
1"
#159
0"
#160
b00000000000000000000000001001001 ,
1"
#161
0"
#162
b00000000000000000000000001001010 ,
1"
#163
0"
#164
b00000000000000000000000001001011 ,
1"
#165
0"
#166
b00000000000000000000000001001100 ,
1"
#167
0"
#168
b00000000000000000000000001001101 ,
1"
#169
0"
#170
b00000000000000000000000001001110 ,
1"
#171
0"
#172
b00000000000000000000000001001111 ,
1"
#173
0"
#174
b00000000000000000000000001010000 ,
1"
#175
0"
#176
b00000000000000000000000001010001 ,
1"
#177
0"
#178
b00000000000000000000000001010010 ,
1"
#179
0"
#180
b00000000000000000000000001010011 ,
1"
#181
0"
#182
b00000000000000000000000001010100 ,
1"
#183
0"
#184
b00000000000000000000000001010101 ,
1"
#185
0"
#186
b00000000000000000000000001010110 ,
1"
#187
0"
#188
b00000000000000000000000001010111 ,
1"
#189
0"
#190
b00000000000000000000000001011000 ,
1"
#191
0"
#192
b00000000000000000000000001011001 ,
1"
#193
0"
#194
b00000000000000000000000001011010 ,
1"
#195
0"
#196
b00000000000000000000000001011011 ,
1"
#197
0"
#198
b00000000000000000000000001011100 ,
1"
#199
0"
#200
b00000000000000000000000001011101 ,
1"
#201
0"
#202
b00000000000000000000000001011110 ,
1"
#203
0"
#204
b00000000000000000000000001011111 ,
1"
#205
0"
#206
b00000000000000000000000001100000 ,
1"
#207
0"
#208
b00000000000000000000000001100001 ,
1"
#209
0"
#210
b00000000000000000000000001100010 ,
1"
#211
0"
#212
b00000000000000000000000001100011 ,
1"
#213
0"
#214
b00000000000000000000000001100100 ,
1"
#215
0"
#216
b00000000000000000000000001100101 ,
1"
#217
0"
#218
b00000000000000000000000001100110 ,
1"
#219
0"
#220
b00000000000000000000000001100111 ,
1"
#221
0"
#222
b00000000000000000000000001101000 ,
1"
#223
0"
#224
b00000000000000000000000001101001 ,
1"
#225
0"
#226
b00000000000000000000000001101010 ,
1"
#227
0"
#228
b00000000000000000000000001101011 ,
1"
#229
0"
#230
b00000000000000000000000001101100 ,
1"
#231
0"
#232
b00000000000000000000000001101101 ,
1"
#233
0"
#234
b00000000000000000000000001101110 ,
1"
#235
0"
#236
b00000000000000000000000001101111 ,
1"
#237
0"
#238
b00000000000000000000000001110000 ,
1"
#239
0"
#240
b00000000000000000000000001110001 ,
1"
#241
0"
#242
b00000000000000000000000001110010 ,
1"
#243
0"
#244
b00000000000000000000000001110011 ,
1"
#245
0"
#246
b00000000000000000000000001110100 ,
1"
#247
0"
#248
b00000000000000000000000001110101 ,
1"
#249
0"
#250
b00000000000000000000000001110110 ,
1"
#251
0"
#252
b00000000000000000000000001110111 ,
1"
#253
0"
#254
b00000000000000000000000001111000 ,
1"
#255
0"
#256
b00000000000000000000000001111001 ,
1"
#257
0"
#258
b00000000000000000000000001111010 ,
1"
#259
0"
#260
b00000000000000000000000001111011 ,
1"
#261
0"
#262
b00000000000000000000000001111100 ,
1"
#263
0"
#264
b00000000000000000000000001111101 ,
1"
#265
0"
#266
b00000000000000000000000001111110 ,
1"
#267
0"
#268
b00000000000000000000000001111111 ,
1"
#269
0"
#270
b00000000000000000000000010000000 ,
1"
#271
0"
#272
b00000000000000000000000010000001 ,
1"
#273
0"
#274
b00000000000000000000000010000010 ,
1"
#275
0"
#276
b00000000000000000000000010000011 ,
1"
#277
0"
#278
b00000000000000000000000010000100 ,
1"
#279
0"
#280
b00000000000000000000000010000101 ,
1"
#281
0"
#282
b00000000000000000000000010000110 ,
1"
#283
0"
#284
b00000000000000000000000010000111 ,
1"
#285
0"
#286
b00000000000000000000000010001000 ,
1"
#287
0"
#288
b00000000000000000000000010001001 ,
1"
#289
0"
#290
b00000000000000000000000010001010 ,
1"
#291
0"
#292
b00000000000000000000000010001011 ,
1"
#293
0"
#294
b00000000000000000000000010001100 ,
1"
#295
0"
#296
b00000000000000000000000010001101 ,
1"
#297
0"
#298
b00000000000000000000000010001110 ,
1"
#299
0"
#300
b00000000000000000000000010001111 ,
1"
#301
0"
#302
b00000000000000000000000010010000 ,
1"
#303
0"
#304
b00000000000000000000000010010001 ,
1"
#305
0"
#306
b00000000000000000000000010010010 ,
1"
#307
0"
#308
b00000000000000000000000010010011 ,
1"
#309
0"
#310
b00000000000000000000000010010100 ,
1"
#311
0"
#312
b00000000000000000000000010010101 ,
1"
#313
0"
#314
b00000000000000000000000010010110 ,
1"
#315
0"
#316
b00000000000000000000000010010111 ,
1"
#317
0"
#318
b00000000000000000000000010011000 ,
1"
#319
0"
#320
b00000000000000000000000010011001 ,
1"
#321
0"
#322
b00000000000000000000000010011010 ,
1"
#323
0"
#324
b00000000000000000000000010011011 ,
1"
#325
0"
#326
b00000000000000000000000010011100 ,
1"
#327
0"
#328
b00000000000000000000000010011101 ,
1"
#329
0"
#330
b00000000000000000000000010011110 ,
1"
#331
0"
#332
b00000000000000000000000010011111 ,
1"
#333
0"
#334
b00000000000000000000000010100000 ,
1"
#335
0"
#336
b00000000000000000000000010100001 ,
1"
#337
0"
#338
b00000000000000000000000010100010 ,
1"
#339
0"
#340
b00000000000000000000000010100011 ,
1"
#341
0"
#342
b00000000000000000000000010100100 ,
1"
#343
0"
#344
b00000000000000000000000010100101 ,
1"
#345
0"
#346
b00000000000000000000000010100110 ,
1"
#347
0"
#348
b00000000000000000000000010100111 ,
1"
#349
0"
#350
b00000000000000000000000010101000 ,
1"
#351
0"
#352
b00000000000000000000000010101001 ,
1"
#353
0"
#354
b00000000000000000000000010101010 ,
1"
#355
0"
#356
b00000000000000000000000010101011 ,
1"
#357
0"
#358
b00000000000000000000000010101100 ,
1"
#359
0"
#360
b00000000000000000000000010101101 ,
1"
#361
0"
#362
b00000000000000000000000010101110 ,
1"
#363
0"
#364
b00000000000000000000000010101111 ,
1"
#365
0"
#366
b00000000000000000000000010110000 ,
1"
#367
0"
#368
b00000000000000000000000010110001 ,
1"
#369
0"
#370
b00000000000000000000000010110010 ,
1"
#371
0"
#372
b00000000000000000000000010110011 ,
1"
#373
0"
#374
b00000000000000000000000010110100 ,
1"
#375
0"
#376
b00000000000000000000000010110101 ,
1"
#377
0"
#378
b00000000000000000000000010110110 ,
1"
#379
0"
#380
b00000000000000000000000010110111 ,
1"
#381
0"
#382
b00000000000000000000000010111000 ,
1"
#383
0"
#384
b00000000000000000000000010111001 ,
1"
#385
0"
#386
b00000000000000000000000010111010 ,
1"
#387
0"
#388
b00000000000000000000000010111011 ,
1"
#389
0"
#390
b00000000000000000000000010111100 ,
1"
#391
0"
#392
b00000000000000000000000010111101 ,
1"
#393
0"
#394
b00000000000000000000000010111110 ,
1"
#395
0"
#396
b00000000000000000000000010111111 ,
1"
#397
0"
#398
b00000000000000000000000011000000 ,
1"
#399
0"
#400
b00000000000000000000000011000001 ,
1"
#401
0"
#402
b00000000000000000000000011000010 ,
1"
#403
0"
#404
b00000000000000000000000011000011 ,
1"
#405
0"
#406
b00000000000000000000000011000100 ,
1"
#407
0"
#408
b00000000000000000000000011000101 ,
1"
#409
0"
#410
b00000000000000000000000011000110 ,
1"
#411
0"
#412
b00000000000000000000000011000111 ,
1"
#413
0"
#414
b00000000000000000000000011001000 ,
1"
#415
0"
#416
b00000000000000000000000011001001 ,
1"
#417
0"
#418
b00000000000000000000000011001010 ,
1"
#419
0"
#420
b00000000000000000000000011001011 ,
1"
#421
0"
#422
b00000000000000000000000011001100 ,
1"
#423
0"
#424
b00000000000000000000000011001101 ,
1"
#425
0"
#426
b00000000000000000000000011001110 ,
1"
#427
0"
#428
b00000000000000000000000011001111 ,
1"
#429
0"
#430
b00000000000000000000000011010000 ,
1"
#431
0"
#432
b00000000000000000000000011010001 ,
1"
#433
0"
#434
b00000000000000000000000011010010 ,
1"
#435
0"
#436
b00000000000000000000000011010011 ,
1"
#437
0"
#438
b00000000000000000000000011010100 ,
1"
#439
0"
#440
b00000000000000000000000011010101 ,
1"
#441
0"
#442
b00000000000000000000000011010110 ,
1"
#443
0"
#444
b00000000000000000000000011010111 ,
1"
#445
0"
#446
b00000000000000000000000011011000 ,
1"
#447
0"
#448
b00000000000000000000000011011001 ,
1"
#449
0"
#450
b00000000000000000000000011011010 ,
1"
#451
0"
#452
b00000000000000000000000011011011 ,
1"
#453
0"
#454
b00000000000000000000000011011100 ,
1"
#455
0"
#456
b00000000000000000000000011011101 ,
1"
#457
0"
#458
b00000000000000000000000011011110 ,
1"
#459
0"
#460
b00000000000000000000000011011111 ,
1"
#461
0"
#462
b00000000000000000000000011100000 ,
1"
#463
0"
#464
b00000000000000000000000011100001 ,
1"
#465
0"
#466
b00000000000000000000000011100010 ,
1"
#467
0"
#468
b00000000000000000000000011100011 ,
1"
#469
0"
#470
b00000000000000000000000011100100 ,
1"
#471
0"
#472
b00000000000000000000000011100101 ,
1"
#473
0"
#474
b00000000000000000000000011100110 ,
1"
#475
0"
#476
b00000000000000000000000011100111 ,
1"
#477
0"
#478
b00000000000000000000000011101000 ,
1"
#479
0"
#480
b00000000000000000000000011101001 ,
1"
#481
0"
#482
b00000000000000000000000011101010 ,
1"
#483
0"
#484
b00000000000000000000000011101011 ,
1"
#485
0"
#486
b00000000000000000000000011101100 ,
1"
#487
0"
#488
b00000000000000000000000011101101 ,
1"
#489
0"
#490
b00000000000000000000000011101110 ,
1"
#491
0"
#492
b00000000000000000000000011101111 ,
1"
#493
0"
#494
b00000000000000000000000011110000 ,
1"
#495
0"
#496
b00000000000000000000000011110001 ,
1"
#497
0"
#498
b00000000000000000000000011110010 ,
1"
#499
0"
#500
b00000000000000000000000011110011 ,
1"
#501
0"
#502
b00000000000000000000000011110100 ,
1"
#503
0"
#504
b00000000000000000000000011110101 ,
1"
#505
0"
#506
b00000000000000000000000011110110 ,
1"
#507
0"
#508
b00000000000000000000000011110111 ,
1"
#509
0"
#510
b00000000000000000000000011111000 ,
1"
#511
0"
#512
b00000000000000000000000011111001 ,
1"
#513
0"
#514
b00000000000000000000000011111010 ,
1"
#515
0"
#516
b00000000000000000000000011111011 ,
1"
#517
0"
#518
b00000000000000000000000011111100 ,
1"
#519
0"
#520
b00000000000000000000000011111101 ,
1"
#521
0"
#522
b00000000000000000000000011111110 ,
1"
#523
0"
#524
b00000000000000000000000011111111 ,
1"
#525
0"
#526
b00000000000000000000000100000000 ,
1"
#527
0"
#528
b00000000000000000000000100000001 ,
1"
#529
0"
#530
b00000000000000000000000100000010 ,
1"
#531
0"
#532
b00000000000000000000000100000011 ,
1"
#533
0"
#534
b00000000000000000000000100000100 ,
1"
#535
0"
#536
b00000000000000000000000100000101 ,
1"
#537
0"
#538
b00000000000000000000000100000110 ,
1"
#539
0"
#540
b00000000000000000000000100000111 ,
1"
#541
0"
#542
b00000000000000000000000100001000 ,
1"
#543
0"
#544
b00000000000000000000000100001001 ,
1"
#545
0"
#546
b00000000000000000000000100001010 ,
1"
#547
0"
